gazo/__init__.py
gazo/main.py
gazo/commands/__init__.py
gazo/commands/display_image.py
gazo-0.1.2.dist-info/LICENSE
gazo-0.1.2.dist-info/METADATA
gazo-0.1.2.dist-info/WHEEL
gazo-0.1.2.dist-info/entry_points.txt
gazo-0.1.2.dist-info/top_level.txt
gazo-0.1.2.dist-info/RECORD
