Metadata-Version: 2.1
Name: gazo
Version: 0.1.2
Summary: A CLI application to display image files in the terminal.
Home-page: https://github.com/suzukitakac/gazo
Author: suzukitakac
Author-email: suzukitakac@outlook.jp
Classifier: Programming Language :: Python :: 3
Classifier: License :: OSI Approved :: MIT License
Classifier: Operating System :: OS Independent
Classifier: Development Status :: 3 - Alpha
Classifier: Intended Audience :: End Users/Desktop
Requires-Python: >=3.6
License-File: LICENSE
Requires-Dist: pillow
